[
  {
    "title": "CAD DESIGNER (2D & 3D)",
    "company": "Kaizen Industries",
    "location": "Remote (Part-Time)"
  },
  {
    "title": "LOGISTICS SUPERVISOR",
    "company": "Booths",
    "location": "United Kingdom"
  },
  {
    "title": "RESEARCH INTERN",
    "company": "University of Lancashire",
    "location": "Preston, United Kingdom"
  },
  {
    "title": "VOLUNTEER CITIZEN SCIENTIST",
    "company": "Zooniverse",
    "location": ""
  },
  {
    "title": "VOLUNTEER CITIZEN SCIENTIST",
    "company": "NASA Globe Mission",
    "location": ""
  },
  {
    "title": "CLASS REPRESENTATIVE",
    "company": "University of Lancashire",
    "location": "Preston, United Kingdom"
  }
]
